twobitreader/__init__.py
twobitreader/__main__.py
twobitreader/download.py
twobitreader-3.1.8.dist-info/licenses/COPYRIGHT
twobitreader-3.1.8.dist-info/licenses/LICENSE.txt
twobitreader-3.1.8.dist-info/METADATA
twobitreader-3.1.8.dist-info/WHEEL
twobitreader-3.1.8.dist-info/top_level.txt
twobitreader-3.1.8.dist-info/RECORD
